.gitignore
CHANGELOG.md
LICENSE
README.md
requirements-dev.txt
requirements.txt
setup.py
.github/workflows/publish.yml
.github/workflows/py3.yml
docs/IPAM.rst
docs/Makefile
docs/advanced.rst
docs/conf.py
docs/endpoint.rst
docs/index.rst
docs/request.rst
docs/response.rst
kani_fork_pynetbox.egg-info/PKG-INFO
kani_fork_pynetbox.egg-info/SOURCES.txt
kani_fork_pynetbox.egg-info/dependency_links.txt
kani_fork_pynetbox.egg-info/not-zip-safe
kani_fork_pynetbox.egg-info/requires.txt
kani_fork_pynetbox.egg-info/top_level.txt
pynetbox/__init__.py
pynetbox/core/__init__.py
pynetbox/core/api.py
pynetbox/core/app.py
pynetbox/core/endpoint.py
pynetbox/core/query.py
pynetbox/core/response.py
pynetbox/core/util.py
pynetbox/models/__init__.py
pynetbox/models/circuits.py
pynetbox/models/dcim.py
pynetbox/models/extras.py
pynetbox/models/ipam.py
pynetbox/models/users.py
pynetbox/models/virtualization.py
pynetbox/models/wireless.py
tests/__init__.py
tests/conftest.py
tests/test_api.py
tests/test_app.py
tests/test_circuits.py
tests/test_tenancy.py
tests/test_users.py
tests/test_virtualization.py
tests/test_wireless.py
tests/util.py
tests/fixtures/api/get_session_key.json
tests/fixtures/api/token_provision.json
tests/fixtures/circuits/circuit.json
tests/fixtures/circuits/circuit_termination.json
tests/fixtures/circuits/circuit_terminations.json
tests/fixtures/circuits/circuit_type.json
tests/fixtures/circuits/circuit_types.json
tests/fixtures/circuits/circuits.json
tests/fixtures/circuits/provider.json
tests/fixtures/circuits/providers.json
tests/fixtures/dcim/cable.json
tests/fixtures/dcim/cables.json
tests/fixtures/dcim/choices.json
tests/fixtures/dcim/console_port.json
tests/fixtures/dcim/console_port_template.json
tests/fixtures/dcim/console_port_templates.json
tests/fixtures/dcim/console_ports.json
tests/fixtures/dcim/console_server_port.json
tests/fixtures/dcim/console_server_port_template.json
tests/fixtures/dcim/console_server_port_templates.json
tests/fixtures/dcim/console_server_ports.json
tests/fixtures/dcim/device.json
tests/fixtures/dcim/device_bay.json
tests/fixtures/dcim/device_bay_template.json
tests/fixtures/dcim/device_bay_templates.json
tests/fixtures/dcim/device_bays.json
