Metadata-Version: 2.1
Name: kani-fork-pynetbox
Version: 6.6.2
Summary: NetBox API client library
Home-page: https://github.com/kani999/pynetbox
Author: Zach Moody
Author-email: zmoody@do.co
License: Apache2
Keywords: netbox
Platform: UNKNOWN
Classifier: Intended Audience :: Developers
Classifier: Development Status :: 5 - Production/Stable
Classifier: Programming Language :: Python :: 2
Classifier: Programming Language :: Python :: 2.7
Classifier: Programming Language :: Python :: 3
Classifier: Programming Language :: Python :: 3.6
License-File: LICENSE
